cpu.v
`timescale 1ns/1ps

//====================================================
// Simple 8-bit CPU (Non-Pipelined)
//====================================================
module SimpleCPU(
    input clk,
    input rst,
    output [7:0] out
);

    reg [3:0] PC;                // Program Counter
    reg [7:0] IMEM [0:15];       // Instruction Memory
    reg [7:0] REG [0:3];         // Register File (R0-R3)
    reg [7:0] instr;             // Current Instruction

    integer i;

    // Program initialization
    initial begin
        IMEM[0] = 8'b10_00_00_01; // MOVI R0,1
        IMEM[1] = 8'b10_01_00_10; // MOVI R1,2
        IMEM[2] = 8'b00_00_01_00; // ADD R0,R1
        IMEM[3] = 8'b01_01_00_00; // SUB R1,R0
        IMEM[4] = 8'b11_00_00_00; // NOP
    end

    always @(posedge clk or posedge rst) begin
        if (rst) begin
            PC <= 0;
            instr <= 0;
            for (i = 0; i < 4; i = i + 1)
                REG[i] <= 0;
        end
        else begin
            // FETCH
            instr <= IMEM[PC];
            PC <= PC + 1;

            // DECODE + EXECUTE
            case (instr[7:6])
                2'b00: REG[instr[5:4]] <= REG[instr[5:4]] + REG[instr[3:2]]; // ADD
                2'b01: REG[instr[5:4]] <= REG[instr[5:4]] - REG[instr[3:2]]; // SUB
                2'b10: REG[instr[5:4]] <= instr[1:0];                       // MOVI
                default: ;                                                  // NOP
            endcase
        end
    end

    assign out = REG[0];  // Observe R0 in waveform

endmodule


//====================================================
// Testbench
//====================================================
module tb_SimpleCPU;

    reg clk;
    reg rst;
    wire [7:0] out;

    // Instantiate CPU
    SimpleCPU uut (
        .clk(clk),
        .rst(rst),
        .out(out)
    );

    // Clock (10ns period)
    initial clk = 0;
    always #5 clk = ~clk;

    initial begin
        $dumpfile("cpu.vcd");
        $dumpvars(0, tb_SimpleCPU);

        // Apply reset
        rst = 1;
        #12;
        rst = 0;

        // Let program run
        #100;

        $finish;
    end

endmodule

cpu.vcd
$date
	Sat Feb 21 12:27:53 2026
$end
$version
	Icarus Verilog
$end
$timescale
	1ps
$end
$scope module tb_SimpleCPU $end
$var wire 8 ! out [7:0] $end
$var reg 1 " clk $end
$var reg 1 # rst $end
$scope module uut $end
$var wire 1 " clk $end
$var wire 8 $ out [7:0] $end
$var wire 1 # rst $end
$var reg 4 % PC [3:0] $end
$var reg 8 & instr [7:0] $end
$var integer 32 ' i [31:0] $end
$upscope $end
$upscope $end
$enddefinitions $end
$comment Show the parameter values. $end
$dumpall
$end
#0
$dumpvars
b100 '
b0 &
b0 %
b0 $
1#
0"
b0 !
$end
#5000
b100 '
1"
#10000
0"
#12000
0#
#15000
b1 %
b10000001 &
1"
#20000
0"
#25000
b1 !
b1 $
b10 %
b10010010 &
1"
#30000
0"
#35000
b11 %
b100 &
1"
#40000
0"
#45000
b11 !
b11 $
b100 %
b1010000 &
1"
#50000
0"
#55000
b101 %
b11000000 &
1"
#60000
0"
#65000
b110 %
bx &
1"
#70000
0"
#75000
b111 %
1"
#80000
0"
#85000
b1000 %
1"
#90000
0"
#95000
b1001 %
1"
#100000
0"
#105000
b1010 %
1"
