pipeline.v
module Pipeline4Stage(
    input clk, rst,
    input [7:0] instr_in,
    output [7:0] out
);
    reg [7:0] IF_ID, ID_EX, EX_WB;

    always @(posedge clk or posedge rst) begin
        if (rst) begin
            IF_ID <= 0;
            ID_EX <= 0;
            EX_WB <= 0;
        end else begin
            IF_ID <= instr_in;
            ID_EX <= IF_ID;
            EX_WB <= ID_EX;
        end
    end

    assign out = EX_WB;
endmodule


//=============================
// Testbench
//=============================
module tb_Pipeline4Stage;
    reg clk, rst;
    reg [7:0] instr_in;
    wire [7:0] out;

    Pipeline4Stage pipe(.clk(clk), .rst(rst), .instr_in(instr_in), .out(out));

    initial clk = 0;
    always #5 clk = ~clk;

    initial begin
        $dumpfile("pipeline4.vcd");
        $dumpvars(0, tb_Pipeline4Stage);

        rst = 1; #10; rst = 0;

        instr_in = 8'd10; #10;
        instr_in = 8'd20; #10;
        instr_in = 8'd30; #10;
        instr_in = 8'd40; #10;

        $finish;
    end
endmodule

pipeline4.vcd
$date
	Sat Feb 21 12:15:59 2026
$end
$version
	Icarus Verilog
$end
$timescale
	1s
$end
$scope module tb_Pipeline4Stage $end
$var wire 8 ! out [7:0] $end
$var reg 1 " clk $end
$var reg 8 # instr_in [7:0] $end
$var reg 1 $ rst $end
$scope module pipe $end
$var wire 1 " clk $end
$var wire 8 % instr_in [7:0] $end
$var wire 8 & out [7:0] $end
$var wire 1 $ rst $end
$var reg 8 ' EX_WB [7:0] $end
$var reg 8 ( ID_EX [7:0] $end
$var reg 8 ) IF_ID [7:0] $end
$upscope $end
$upscope $end
$enddefinitions $end
$comment Show the parameter values. $end
$dumpall
$end
#0
$dumpvars
b0 )
b0 (
b0 '
b0 &
bx %
1$
bx #
0"
b0 !
$end
#5
1"
#10
0"
b1010 #
b1010 %
0$
#15
b1010 )
1"
#20
0"
b10100 #
b10100 %
#25
b1010 (
b10100 )
1"
#30
0"
b11110 #
b11110 %
#35
b1010 !
b1010 &
b1010 '
b10100 (
b11110 )
1"
#40
0"
b101000 #
b101000 %
#45
b10100 !
b10100 &
b10100 '
b11110 (
b101000 )
1"
